README.rst
setup.py
scientpyfic_cli/__init__.py
scientpyfic_cli.egg-info/PKG-INFO
scientpyfic_cli.egg-info/SOURCES.txt
scientpyfic_cli.egg-info/dependency_links.txt
scientpyfic_cli.egg-info/entry_points.txt
scientpyfic_cli.egg-info/requires.txt
scientpyfic_cli.egg-info/top_level.txt
scientpyfic_cli.egg-info/zip-safe