Metadata-Version: 1.1
Name: scientpyfic-cli
Version: 0.0.0
Summary: Latest science news on your prompt/shell.
Home-page: https://github.com/monzita/scientpyfic-cli
Author: Monika Ilieva
Author-email: hidden@hidden.com
License: MIT
Keywords: cli scientpyfic science daily python beautifulsoup
Platform: UNKNOWN
Classifier: Development Status :: 3 - Alpha
Classifier: Environment :: Console
Classifier: Intended Audience :: Developers
Classifier: License :: OSI Approved :: MIT License
Classifier: Programming Language :: Python :: 3.5
Classifier: Programming Language :: Python :: 3.6
Classifier: Programming Language :: Python :: 3.7
Classifier: Programming Language :: Python :: 3 :: Only
Classifier: Topic :: Utilities
